noaapi/__init__.py
noaapi/main.py
noaapi-0.0.6.dist-info/METADATA
noaapi-0.0.6.dist-info/WHEEL
noaapi-0.0.6.dist-info/entry_points.txt
noaapi-0.0.6.dist-info/top_level.txt
noaapi-0.0.6.dist-info/RECORD
